riverine/CHANGELOG.md
riverine/__init__.py
riverine/_version.py
riverine/abbreviated.py
riverine/actions.py
riverine/components.py
riverine/dictstructure.py
riverine/echo.py
riverine/experiments.py
riverine/locations.py
riverine/logging.py
riverine/mixes.py
riverine/printing.py
riverine/quantitate.py
riverine/references.py
riverine/units.py
riverine/util.py
riverine-0.7.0.dist-info/METADATA
riverine-0.7.0.dist-info/WHEEL
riverine-0.7.0.dist-info/licenses/LICENSE.txt
riverine-0.7.0.dist-info/RECORD
