Metadata-Version: 2.4
Name: riverine
Version: 0.7.0
Summary: Many-component mix library for molecular programming
Project-URL: Homepage, https://github.com/cgevans/mixes
Project-URL: Documentation, https://riverine.readthedocs.io
Project-URL: Repository, https://github.com/cgevans/mixes.git
Project-URL: Issues, https://github.com/cgevans/issues
Project-URL: source_archive, https://github.com/org/repo/archive/eb3fb6c00f12577be4a1d48c94b83fa539771609.zip
Author-email: Constantine Evans <mixes@mb.costi.net>
License: BSD 3-Clause License
License-File: LICENSE.txt
Classifier: Development Status :: 4 - Beta
Classifier: Intended Audience :: Science/Research
Classifier: License :: OSI Approved :: BSD License
Classifier: Programming Language :: Python :: 3.10
Classifier: Programming Language :: Python :: 3.11
Classifier: Programming Language :: Python :: 3.12
Classifier: Programming Language :: Python :: 3.13
Classifier: Programming Language :: Python :: 3.14
Classifier: Topic :: Scientific/Engineering
Classifier: Typing :: Typed
Requires-Python: >=3.10
Requires-Dist: attrs>=22.1
Requires-Dist: kithairon>=0.2.0
Requires-Dist: numpy
Requires-Dist: openpyxl
Requires-Dist: pandas
Requires-Dist: pint>=0.20
Requires-Dist: polars[numpy,pandas]~=1.4
Requires-Dist: tabulate
Requires-Dist: toml
Requires-Dist: typing-extensions>=4.2
Provides-Extra: all
Provides-Extra: docs
Requires-Dist: matplotlib; extra == 'docs'
Requires-Dist: myst-parser; extra == 'docs'
Requires-Dist: numpydoc; extra == 'docs'
Requires-Dist: sphinx-autoapi; extra == 'docs'
Requires-Dist: sphinx-book-theme; extra == 'docs'
Provides-Extra: testing
Requires-Dist: pytest; extra == 'testing'
Requires-Dist: pytest-cov; extra == 'testing'
Requires-Dist: setuptools; extra == 'testing'
